cbcbase/__init__.py
cbcbase/cb_session.py
cbcbase/exceptions.py
cbcbase/logic/__init__.py
cbcbase/logic/cb_index.py
cbcbase/logic/config.py
cbcbase/logic/constants.py
cbcbase/logic/key_styles.py
cbcbase-1.0.0.dist-info/METADATA
cbcbase-1.0.0.dist-info/WHEEL
cbcbase-1.0.0.dist-info/RECORD
